deep_collection/__init__.py
deep_collection/__init__.pyx
deep_collection-0.2.0b1.dist-info/LICENSE
deep_collection-0.2.0b1.dist-info/WHEEL
deep_collection-0.2.0b1.dist-info/METADATA
deep_collection-0.2.0b1.dist-info/RECORD
